photon_canon/__init__.py
photon_canon/hardware.py
photon_canon/import_utils.py
photon_canon/optics.py
photon_canon/utils.py
photon_canon/contrib/__init__.py
photon_canon/contrib/bio.py
photon_canon/contrib/diffusion_theory.py
photon_canon/contrib/food_coloring.py
photon_canon/data/hbo2_hb.tsv
photon_canon/data/sample_food_coloring_absorption.csv
photon_canon/data/validation_stock_absorbance.csv
photon_canon/lut/__init__.py
photon_canon/lut/lut.py
photon_canon/lut/utils.py
photon_canon/scripts/generate_lut.py
photon_canon-2.1.1.dist-info/licenses/LICENSE.txt
photon_canon-2.1.1.dist-info/METADATA
photon_canon-2.1.1.dist-info/WHEEL
photon_canon-2.1.1.dist-info/top_level.txt
photon_canon-2.1.1.dist-info/RECORD
