Metadata-Version: 2.4
Name: photon_canon
Version: 2.1.1
Summary: An in-depth 3D Monte Carlo simulation toolbox with custom systems of planar mediums, custom beams and detectors.
Author-email: Jesse D Ivers <iversjesse@gmail.com>
License:                     GNU GENERAL PUBLIC LICENSE
Project-URL: Homepage, https://www.github.com/jiversivers/monte_carlo
Project-URL: Source, https://www.github.com/jiversivers/monte_carlo
Project-URL: Check me out, https://www.jivers.me
Keywords: simulation,parallel,monte carlo,photon
Requires-Python: >=3
License-File: LICENSE.txt
Requires-Dist: matplotlib==3.10.3
Requires-Dist: numpy==2.3.1
Requires-Dist: pandas==2.3.0
Requires-Dist: pydantic==2.11.7
Requires-Dist: scipy==1.16.0
Requires-Dist: tqdm==4.67.1
Provides-Extra: cuda
Requires-Dist: cupy; extra == "cuda"
Provides-Extra: dev
Requires-Dist: toml; extra == "dev"
Provides-Extra: test
Requires-Dist: unittest; extra == "test"
Dynamic: license-file
